flerken/__init__.py
flerken/_version.py
flerken/audio/__init__.py
flerken/dataloaders/__init__.py
flerken/dataloaders/transforms/__init__.py
flerken/dataloaders/transforms/transforms.py
flerken/datasets/__init__.py
flerken/datasets/dataset_tools.py
flerken/datasets/hmdb51/__init__.py
flerken/datasets/hmdb51/hmdb51.py
flerken/datasets/hmdb51/hmdb51_json.py
flerken/datasets/hmdb51/n_frames_ucf101_hmdb51.py
flerken/datasets/hmdb51/spatial_transforms.py
flerken/datasets/hmdb51/target_transforms.py
flerken/datasets/hmdb51/temporal_transforms.py
flerken/datasets/hmdb51/video_jpg_ucf101_hmdb51.py
flerken/framework/__init__.py
flerken/framework/classitems.py
flerken/framework/decorators.py
flerken/framework/network_initialization.py
flerken/framework/pytorchframework.py
flerken/framework/sqlite_tools.py
flerken/framework/traceback_gradients.py
flerken/framework/utils.py
flerken/models/ResNet3D.py
flerken/models/UNet.py
flerken/models/VGG.py
flerken/models/__init__.py
flerken/utils/__init__.py
flerken/utils/losses.py
flerken/video/__init__.py
flerken-0.2.4.post4.dist-info/METADATA
flerken-0.2.4.post4.dist-info/WHEEL
flerken-0.2.4.post4.dist-info/top_level.txt
flerken-0.2.4.post4.dist-info/RECORD
